ipylgbst/__init__.py
ipylgbst/_frontend.py
ipylgbst/_version.py
ipylgbst/lego_boost.py
ipylgbst/nbextension/extension.js
ipylgbst/nbextension/index.js
ipylgbst/nbextension/index.js.LICENSE.txt
ipylgbst/nbextension/index.js.map
ipylgbst/tests/__init__.py
ipylgbst/tests/conftest.py
ipylgbst/tests/test_nbextension_path.py
ipylgbst/tests/test_widget.py
ipylgbst-0.3.1.data/data/share/jupyter/labextensions/ipylgbst/package.json
ipylgbst-0.3.1.data/data/share/jupyter/labextensions/ipylgbst/static/25.9a30fe8f31510338c83b.js
ipylgbst-0.3.1.data/data/share/jupyter/labextensions/ipylgbst/static/251.7cecff9b2814cfdd2c4b.js
ipylgbst-0.3.1.data/data/share/jupyter/labextensions/ipylgbst/static/251.7cecff9b2814cfdd2c4b.js.LICENSE.txt
ipylgbst-0.3.1.data/data/share/jupyter/labextensions/ipylgbst/static/306.e8eb7f60b4f20cd8b34f.js
ipylgbst-0.3.1.data/data/share/jupyter/labextensions/ipylgbst/static/509.80ee419853ac9145f815.js
ipylgbst-0.3.1.data/data/share/jupyter/labextensions/ipylgbst/static/96.e1e2191fc42b1f555334.js
ipylgbst-0.3.1.data/data/share/jupyter/labextensions/ipylgbst/static/96.e1e2191fc42b1f555334.js.LICENSE.txt
ipylgbst-0.3.1.data/data/share/jupyter/labextensions/ipylgbst/static/remoteEntry.3d493ab0c413e3b9d6dd.js
ipylgbst-0.3.1.data/data/share/jupyter/labextensions/ipylgbst/static/style.js
ipylgbst-0.3.1.data/data/share/jupyter/labextensions/ipylgbst/static/third-party-licenses.json
ipylgbst-0.3.1.data/data/share/jupyter/nbextensions/ipylgbst/extension.js
ipylgbst-0.3.1.data/data/share/jupyter/nbextensions/ipylgbst/index.js
ipylgbst-0.3.1.data/data/share/jupyter/nbextensions/ipylgbst/index.js.LICENSE.txt
ipylgbst-0.3.1.data/data/share/jupyter/nbextensions/ipylgbst/index.js.map
ipylgbst-0.3.1.data/data/etc/jupyter/nbconfig/notebook.d/ipylgbst.json
ipylgbst-0.3.1.data/data/share/jupyter/labextensions/ipylgbst/install.json
ipylgbst-0.3.1.dist-info/METADATA
ipylgbst-0.3.1.dist-info/WHEEL
ipylgbst-0.3.1.dist-info/licenses/LICENSE
ipylgbst-0.3.1.dist-info/licenses/LICENSE.txt
ipylgbst-0.3.1.dist-info/RECORD
