Metadata-Version: 2.3
Name: ipylgbst
Version: 0.3.1
Summary: A widget library for controlling LEGO® BOOST via web-bluetooth
Project-URL: Homepage, https://github.com/jupyter-robotics/ipylgbst
Project-URL: Bug Tracker, https://github.com/jupyter-robotics/ipylgbst/issues
Project-URL: Repository, https://github.com/jupyter-robotics/ipylgbst
Author-email: Thorsten Beier <derthorstenbeier@gmail.com>
License: BSD 3-Clause License
License-File: LICENSE
License-File: LICENSE.txt
Keywords: jupyter,jupyterlab,jupyterlab-extension,widgets
Classifier: Framework :: Jupyter
Classifier: Framework :: Jupyter :: JupyterLab
Classifier: Framework :: Jupyter :: JupyterLab :: 4
Classifier: Framework :: Jupyter :: JupyterLab :: Extensions
Classifier: Framework :: Jupyter :: JupyterLab :: Extensions :: Prebuilt
Classifier: License :: OSI Approved :: BSD License
Classifier: Programming Language :: Python
Classifier: Programming Language :: Python :: 3
Classifier: Programming Language :: Python :: 3.8
Classifier: Programming Language :: Python :: 3.9
Classifier: Programming Language :: Python :: 3.10
Classifier: Programming Language :: Python :: 3.11
Classifier: Programming Language :: Python :: 3.12
Requires-Python: >=3.8
Provides-Extra: docs
Requires-Dist: jupyter-sphinx; extra == 'docs'
Requires-Dist: nbsphinx; extra == 'docs'
Requires-Dist: nbsphinx-link; extra == 'docs'
Requires-Dist: pypandoc; extra == 'docs'
Requires-Dist: pytest-check-links; extra == 'docs'
Requires-Dist: recommonmark; extra == 'docs'
Requires-Dist: sphinx-rtd-theme; extra == 'docs'
Requires-Dist: sphinx>=1.5; extra == 'docs'
Provides-Extra: examples
Provides-Extra: test
Requires-Dist: nbval; extra == 'test'
Requires-Dist: pytest-cov; extra == 'test'
Requires-Dist: pytest>=6.0; extra == 'test'
